formatted_console_output/__init__.py
formatted_console_output/formatted_console_output.py
formatted_console_output/test.py
formatted_console_output-0.4.3.dist-info/LICENSE
formatted_console_output-0.4.3.dist-info/METADATA
formatted_console_output-0.4.3.dist-info/WHEEL
formatted_console_output-0.4.3.dist-info/top_level.txt
formatted_console_output-0.4.3.dist-info/RECORD
