Metadata-Version: 2.1
Name: formatted_console_output
Version: 0.4.3
Summary: A package for formatted console output using ANSI escape codes - colors and formatting.
Author: Wesley Marmon
Author-email: wcmarmon@gmail.com
Classifier: Programming Language :: Python :: 3
Classifier: License :: OSI Approved :: MIT License
Classifier: Operating System :: OS Independent
Requires-Python: >=3.6
License-File: LICENSE
